Metadata-Version: 2.1
Name: ithildin
Version: 0.2.7
Summary: Semantic analyzer of EVM bytecode based on Mythril
Home-page: https://github.com/metagon/ithildin
Author: Philippos Gorgoris
Author-email: philippos@gorgoris.com
License: MIT
Platform: UNKNOWN
Classifier: License :: OSI Approved :: MIT License
Classifier: Development Status :: 2 - Pre-Alpha
Classifier: Intended Audience :: Science/Research
Classifier: Programming Language :: Python :: 3.6
Classifier: Programming Language :: Python :: 3.7
Classifier: Programming Language :: Python :: 3.8
Requires-Python: >=3.6.0
Requires-Dist: Jinja2 (==2.11.2)
Requires-Dist: mythril (==0.22.14)
Requires-Dist: SQLAlchemy (==1.3.22)
